sthg_ontology_base/__init__.py
sthg_ontology_base/example/__init__.py
sthg_ontology_base/example/simple_test.py
sthg_ontology_base/example/test_all_types_complete.py
sthg_ontology_base/example/test_base_crud.py
sthg_ontology_base/example/test_base_decorator.py
sthg_ontology_base/example/test_complete.py
sthg_ontology_base/example/test_snowflake.py
sthg_ontology_base/example/test_utils.py
sthg_ontology_base/function/__init__.py
sthg_ontology_base/function/aggregation_types.py
sthg_ontology_base/function/api.py
sthg_ontology_base/function/base.py
sthg_ontology_base/function/collection_types.py
sthg_ontology_base/function/ontology_types.py
sthg_ontology_base/function/optional_types.py
sthg_ontology_base/function/primitive_types.py
sthg_ontology_base/function/registry.py
sthg_ontology_base/utils/__init__.py
sthg_ontology_base/utils/base_crud.py
sthg_ontology_base/utils/base_decorator.py
sthg_ontology_base/utils/registry.py
sthg_ontology_base/utils/snowflake_generator.py
sthg_ontology_base_plus/__init__.py
sthg_ontology_base_plus/example/__init__.py
sthg_ontology_base_plus/example/simple_test.py
sthg_ontology_base_plus/example/test_all_types_complete.py
sthg_ontology_base_plus/example/test_base_crud.py
sthg_ontology_base_plus/example/test_base_decorator.py
sthg_ontology_base_plus/example/test_complete.py
sthg_ontology_base_plus/example/test_snowflake.py
sthg_ontology_base_plus/example/test_utils.py
sthg_ontology_base_plus/function/__init__.py
sthg_ontology_base_plus/function/aggregation_types.py
sthg_ontology_base_plus/function/api.py
sthg_ontology_base_plus/function/base.py
sthg_ontology_base_plus/function/collection_types.py
sthg_ontology_base_plus/function/ontology_types.py
sthg_ontology_base_plus/function/optional_types.py
sthg_ontology_base_plus/function/primitive_types.py
sthg_ontology_base_plus/function/registry.py
sthg_ontology_base_plus/utils/__init__.py
sthg_ontology_base_plus/utils/base_crud.py
sthg_ontology_base_plus/utils/base_decorator.py
sthg_ontology_base_plus-0.0.29.2.dist-info/METADATA
sthg_ontology_base_plus-0.0.29.2.dist-info/WHEEL
sthg_ontology_base_plus-0.0.29.2.dist-info/top_level.txt
sthg_ontology_base_plus-0.0.29.2.dist-info/RECORD
